<?xml version="1.0" encoding="utf-8"?>
<cms.contentitem>
  <ContentItemChannelID>
    <CodeName>NACSMagazine</CodeName>
    <GUID>eecfdedc-a92f-48b7-9daa-eab81c106019</GUID>
    <ObjectType>cms.channel</ObjectType>
  </ContentItemChannelID>
  <ContentItemContentTypeID>
    <CodeName>NACSMagazine.LandingPage</CodeName>
    <GUID>5068cb57-f300-45d6-b038-c429dbacb4cf</GUID>
    <ObjectType>cms.contenttype</ObjectType>
  </ContentItemContentTypeID>
  <ContentItemGUID>d0b2db1f-bc9d-488f-b62a-5c07f7c09df8</ContentItemGUID>
  <ContentItemIsReusable>False</ContentItemIsReusable>
  <ContentItemIsSecured>False</ContentItemIsSecured>
  <ContentItemName>PageNotFound-fsi1kxgj</ContentItemName>
</cms.contentitem>